{
	"info": {
		"_postman_id": "e8f1f57a-62d1-4e60-b77a-a8644707cbc1",
		"name": "API A Friend for Life (N703)",
		"description": "Coleção de requisições para testar os endpoints GET da API da plataforma de adoção de animais 'A Friend for Life'.",
		"schema": "https://schema.getpostman.com/json/collection/v2.1.0/collection.json"
	},
	"item": [
		{
			"name": "Listar todos os pets",
			"request": {
				"method": "GET",
				"header": [],
				"url": {
					"raw": "http://127.0.0.1:8000/api/pets/",
					"protocol": "http",
					"host": [
						"127",
						"0",
						"0",
						"1"
					],
					"port": "8000",
					"path": [
						"api",
						"pets",
						""
					]
				}
			},
			"response": []
		},
		{
			"name": "Obter detalhes de um pet",
			"request": {
				"method": "GET",
				"header": [],
				"url": {
					"raw": "http://127.0.0.1:8000/api/pets/1/",
					"protocol": "http",
					"host": [
						"127",
						"0",
						"0",
						"1"
					],
					"port": "8000",
					"path": [
						"api",
						"pets",
						"1",
						""
					]
				}
			},
			"response": []
		}
	]
}